<root>
<forenames>
<male>
<name n="Terry"/>
<name n="Fremdrick"/>
<name n="Casper"/>
<name n="Cray"/>
<name n="Johnny"/>
<name n="Vilthrank"/>
<name n="Caldmad"/>
<name n="Onu"/>
<name n="Scrumpo"/>
<name n="Granite"/>
<name n="Norbert"/>
</male>
<female>
<name n="Astris"/>
<name n="Tillyin"/>
<name n="Aoife"/>
<name n="Primrose"/>
<name n="Nareria"/>
<name n="Mynne"/>
<name n="Monika"/>
<name n="Balogare"/>
<name n="Fvera"/>
<name n="Zloye"/>
</female>
</forenames>
<surnames>
<name n="Loop"/>
<name n="Diamondhand"/>
<name n="Forrest"/>
<name n="Oundim"/>
<name n="Lee"/>
<name n="Kaelmis"/>
<name n="Bellman"/>
<name n="Shaw"/>
<name n="Nios"/>
<name n="Wise"/>
<name n="Benac"/>
<name n="Bennett"/>
<name n="Bingley"/>
<name n="Ravinacc"/>
<name n="Hobbes"/>
<name n="Flynnt"/>
<name n="Otylugh"/>
<name n="Oldmyer"/>
<name n="Eisenburg"/>
<name n="Bradford"/>
</surnames>
</root>